APP/__init__.py
APP/config.py
APP/main.py
APP/models/__init__.py
APP/models/post.py
APP/scrapers/__init__.py
APP/scrapers/find_boards.py
APP/scrapers/get_board_links.py
APP/scrapers/index_posts.py
APP/scrapers/scrape.py
APP/utils/__init__.py
APP/utils/db_close.py
APP/utils/download.py
APP/utils/logger.py
APP/utils/make_async.py
APP/utils/menu.py
APP/utils/profiles.py
APP/utils/sanitize_path.py
AIBS-0.0.67.dist-info/LICENSE
AIBS-0.0.67.dist-info/METADATA
AIBS-0.0.67.dist-info/WHEEL
AIBS-0.0.67.dist-info/entry_points.txt
AIBS-0.0.67.dist-info/top_level.txt
AIBS-0.0.67.dist-info/RECORD
