Metadata-Version: 2.1
Name: AIBS
Version: 0.0.67
Summary: A simple, database-centered scraper for anonib.
Home-page: https://github.com/taux1c/AIBS
Author: Taux1c
Author-email: taux1c.software@protonmail.com
License: MIT
License-File: LICENSE
Requires-Dist: aiofiles ~=23.2.1
Requires-Dist: SQLAlchemy ~=2.0.23
Requires-Dist: httpx ~=0.25.1
Requires-Dist: tqdm ~=4.66.1
Requires-Dist: beautifulsoup4 ~=4.12.2
